
{
  "educational": [
    {
      "id": "edu_periodic_checkups",
      "title": "الفحوصات الدورية لمرضى السكري (Habits: Periodic Check-ups)",
      "summary": "دليل موجز للفحوصات الدورية: السكر التراكمي HbA1c، سكر الدم الصائم FBG، والزلال في البول UACR مع وظائف الكلى (eGFR). متى تُجرى ولماذا.",
      "images": [
        "https://i.ibb.co/PvkLFMR2/Screenshot-2025-11-19-215320.png",
        "https://i.ibb.co/67MWnb7Y/Screenshot-2025-11-19-214937.png",
        "https://i.ibb.co/chhN6T1Q/Screenshot-2025-11-19-214918.png"
      ],
      "content": [
        { "type": "header", "value": "تحليل السكر التراكمي (HbA1c / A1C)" },
        {
          "type": "paragraph",
          "value": "هو فحص يقيس متوسط مستوى سكر الدم (الجلوكوز) خلال الأشهر الثلاثة الماضية. يرتبط سكر الدم بالهيموغلوبين الموجود في خلايا الدم الحمراء؛ وكلما ارتفع مستوى السكر في الدم زادت كمية الهيموغلوبين المُسَكَّر (HbA1c)."
        },
        {
          "type": "bullets",
          "value": "يُستخدم هذا التحليل لـ: تشخيص داء السكري أو ما قبل السكري؛ متابعة مدى نجاح خطة علاج السكري.",
          "items": [
            "تشخيص داء السكري أو مرحلة ما قبل السكري.",
            "متابعة مدى نجاح خطة علاج مريض السكري."
          ]
        },
        {
          "type": "bullets",
          "value": "تكرار الفحص: عادة كل 6 أشهر إذا كان سكر الدم مستقراً وتحت السيطرة. كل 3 أشهر إذا كان غير مستقر أو عند تغيير الخطة العلاجية.",
          "items": [
            "عادةً يُجرى كل 6 أشهر إذا كان مستوى السكر تحت السيطرة ومستقرًا.",
            "يُجرى كل 3 أشهر إذا كانت هناك تغييرات في الخطة العلاجية أو كان مستوى السكر غير مستقر."
          ]
        },
        {
          "type": "image",
          "value": "https://i.ibb.co/PvkLFMR2/Screenshot-2025-11-19-215320.png"
        },

        { "type": "header", "value": "سكر الدم الصائم (Fasting Blood Glucose)" },
        {
          "type": "paragraph",
          "value": "قياس مستوى سكر الدم بعد صيام لا يقل عن 8 ساعات (عادة طوال الليل). يُستخدم لتشخيص السكري أو مرحلة ما قبل السكري، وكذلك لمتابعة الاستجابة للعلاج (الأنسولين أو الأدوية الفموية)."
        },
        {
          "type": "bullets",
          "value": "تكرار الفحص: للتشخيص يُجرى مرة واحدة أو مرتين للتأكيد. للمتابعة: حسب توجيه الطبيب وقد يكون في المنزل باستخدام جهاز القياس اليومي أو دوريًا في المختبر.",
          "items": [
            "لأغراض التشخيص: مرة واحدة أو مرتين للتأكيد.",
            "للمتابعة: حسب توجيه الطبيب—قد يكون يوميًا/أسبوعيًا عبر جهاز منزلي أو بشكل مخبري دوري."
          ]
        },

        { "type": "header", "value": "الزلال في البول (UACR) ووظائف الكلى" },
        {
          "type": "paragraph",
          "value": "يفحص وجود كميات دقيقة من الألبومين في البول (ألبومين البول الدقيق). في الحالة الطبيعية تُصفّي الكلى الألبومين فلا يظهر في البول بكميات كبيرة؛ ووجوده قد يشير إلى بداية تأثر كلوي مرتبط بالسكري."
        },
        {
          "type": "bullets",
          "value": "اختبارات مرتبطة بوظائف الكلى:",
          "items": [
            "نسبة ألبومين البول إلى الكرياتينين (UACR): تقيس مقدار الألبومين مقارنة بالكرياتينين في عينة بول لبيان كفاءة عمل الكلى.",
            "كرياتينين الدم ومعدل الترشيح الكبيبي المُقدّر (eGFR): يُحسب اعتمادًا على كرياتينين الدم ويعد مؤشرًا على سرعة ترشيح الفضلات؛ الانخفاض يعني تراجع كفاءة الكلى."
          ]
        },
        {
          "type": "bullets",
          "value": "تكرار الفحص: يُوصى بإجراء UACR و eGFR مرة واحدة سنويًا على الأقل لجميع مرضى السكري، أو وفق الحالة السريرية.",
          "items": [
            "مرة واحدة سنويًا على الأقل لجميع مرضى السكري.",
            "قد يوصي الطبيب بتكرار أعلى وفقًا للحالة السريرية."
          ]
        }
      ]
    },

    {
      "id": "edu_diabetes_types",
      "title": "أنواع مرض السكري والفروق بينها",
      "summary": "عرض مبسّط لأنواع السكري: النوع الأول، النوع الثاني، وسكري الحمل؛ الآليات والعلاج والسمات المميزة.",
      "images": [
        "https://i.ibb.co/5gJMf0Q7/Screenshot-2025-11-19-215235.png",
        "https://i.ibb.co/1fqnhDwn/Screenshot-2025-11-19-214900.png"
      ],
      "content": [
        { "type": "header", "value": "النوع الأول من السكري (Type 1 Diabetes)" },
        {
          "type": "paragraph",
          "value": "مرض مناعي ذاتي يهاجم فيه جهاز المناعة خلايا البنكرياس المنتِجة للأنسولين، فيتوقف البنكرياس عن إنتاج الأنسولين أو ينتجه بكميات قليلة جدًا. غالبًا يُشخَّص عند الأطفال واليافعين، ويستلزم علاجًا بالأنسولين طيلة الحياة (حقن)."
        },
        {
          "type": "image",
          "value": "https://i.ibb.co/ZRSccNhx/image.png"
        },

        { "type": "header", "value": "النوع الثاني من السكري (Type 2 Diabetes)" },
        {
          "type": "paragraph",
          "value": "الأشيع انتشارًا، وينجم أساسًا عن مشكلتين: مقاومة الأنسولين (عدم استجابة الخلايا—كالعضلات والكبد والدهون—للأنسولين بالشكل الكافي) مع نقص تدريجي في إنتاج الأنسولين من البنكرياس."
        },
        {
          "type": "bullets",
          "value": "عوامل مرتبطة: السمنة، قلة النشاط البدني، الاستعداد الوراثي.",
          "items": [
            "السمنة وزيادة الوزن.",
            "قلة النشاط البدني.",
            "عوامل وراثية."
          ]
        },
        {
          "type": "paragraph",
          "value": "يُشخَّص غالبًا لدى البالغين. يُعالج بتغيير نمط الحياة والأدوية الفموية، وقد يستلزم لاحقًا حقن الأنسولين."
        },

        { "type": "header", "value": "سكري الحمل (Gestational Diabetes)" },
        {
          "type": "paragraph",
          "value": "يظهر لأول مرة أثناء الحمل، وغالبًا يختفي بعد الولادة، لكنه يرفع خطر تطوّر النوع الثاني مستقبلًا. يتطلّب متابعة دقيقة وعلاجًا مناسبًا لضمان صحة الأم والجنين طوال فترة الحمل."
        }
      ]
    },

    {
      "id": "edu_glucose_devices",
      "title": "أجهزة قياس سكر الدم والفروق بينها",
      "summary": "مقارنة بين جهاز القياس التقليدي (وخز الإصبع) وأنظمة المراقبة المستمرة CGM، مع أمثلة شائعة في السوق المصري.",
      "images": [
        "https://i.ibb.co/7qBknkv/Screenshot-2025-11-19-215111.png",
        "https://i.ibb.co/k2GFbntv/Screenshot-2025-11-19-214849.png",
        "https://i.ibb.co/1fqnhDwn/Screenshot-2025-11-19-214900.png"
      ],
      "content": [
        {
          "type": "header",
          "value": "جهاز قياس سكر الدم التقليدي (Standard Blood Glucose Meter)"
        },
        {
          "type": "paragraph",
          "value": "يتكون عادةً من: الجهاز، وقلم الوخز، وإبر الوخز، وشرائط القياس. تُسحب قطرة دم من طرف الإصبع وتوضع على الشريط المُدخل في الجهاز لتظهر القراءة خلال ثوانٍ."
        },
        {
          "type": "paragraph",
          "value": "أمثلة شائعة في السوق المصري: Accu-Chek (Instant/Guide/Active)، OneTouch (Select Plus)، Contour (TS/Plus One)."
        },
        {
          "type": "image",
          "value": "https://i.ibb.co/k2GFbntv/Screenshot-2025-11-19-214849.png"
        },

        {
          "type": "header",
          "value": "المراقبة المستمرة للسكر (CGM: Continuous Glucose Monitoring)"
        },
        {
          "type": "paragraph",
          "value": "يُثبَّت حساس صغير تحت الجلد (غالبًا في الذراع الخلفية) لقياس الجلوكوز في السائل الخلالي بشكل مستمر. تُقرأ القيم عبر مسح ضوئي متقطع أو بث لاسلكي إلى جهاز استقبال/هاتف ذكي."
        },
        {
          "type": "paragraph",
          "value": "من الأمثلة: FreeStyle Libre (نظام Flash) حيث تُستخرج القراءة عبر المسح."
        },
        {
          "type": "image",
          "value": "https://i.ibb.co/1fqnhDwn/Screenshot-2025-11-19-214900.png"
        },
        {
          "type": "bullets",
          "value": "ميزة إضافية: اتجاهات صعود/هبوط الجلوكوز تُساعِد على اتخاذ قرارات استباقية.",
          "items": [
            "إظهار اتجاهات الجلوكوز صعودًا/هبوطًا.",
            "تنبيهات في بعض الأنظمة عند الارتفاع/الانخفاض."
          ]
        }
      ]
    },

    {
      "id": "edu_insulin_syringes",
      "title": "فروق بين محاقن الأنسولين (Insulin Syringes)",
      "summary": "تفاصيل أحجام وأطوال وإبر محاقن الأنسولين وتأثيرها على الراحة والدقة.",
      "images": [
        "https://i.ibb.co/PvkLFMR2/Screenshot-2025-11-19-215320.png"
      ],
      "content": [
        {
          "type": "paragraph",
          "value": "أدوات حقن تُستخدم لحقن الأنسولين تحت الجلد. الفروق الرئيسية:"
        },
        {
          "type": "image",
          "value": "https://i.ibb.co/PvkLFMR2/Screenshot-2025-11-19-215320.png"
        },
        {
          "type": "bullets",
          "value": "السعة (مل): 0.3 مل للجرعات الصغيرة (< 30 وحدة)؛ 0.5 مل للجرعات المتوسطة (< 50 وحدة)؛ 1 مل للجرعات الكبيرة (< 100 وحدة).",
          "items": [
            "0.3 مل: غالبًا للجرعات الصغيرة (أقل من 30 وحدة).",
            "0.5 مل: للجرعات المتوسطة (أقل من 50 وحدة).",
            "1.0 مل: للجرعات الكبيرة (أقل من 100 وحدة)."
          ]
        },
        {
          "type": "bullets",
          "value": "طول الإبرة (مم): 4، 5، 6، 8، 12.7 مم. الإبر الأقصر (4–5 مم) مفضّلة لمعظم البالغين والأطفال لتقليل خطر الحقن في العضل.",
          "items": [
            "أطوال شائعة: 4، 5، 6، 8، 12.7 مم.",
            "الإبر الأقصر تقلل خطر الحقن العضلي غير المرغوب."
          ]
        },
        {
          "type": "bullets",
          "value": "مقياس السُمك (Gauge): كلما زاد رقم G كانت الإبرة أنحف (مثل 29G/30G/31G)، وغالبًا أكثر راحة وأقل ألمًا.",
          "items": [
            "مقاييس شائعة: 29G، 30G، 31G.",
            "الإبرة الأنحف غالبًا أريح وأقل ألمًا."
          ]
        }
      ]
    },

    {
      "id": "edu_insulin_pen",
      "title": "قلم الأنسولين (Insulin Pen)",
      "summary": "وصف قلم الأنسولين وآلية عمله وخصائصه العملية مقارنة بالحقن التقليدية.",
      "images": [
        "https://i.ibb.co/1fqnhDwn/Screenshot-2025-11-19-214900.png"
      ],
      "content": [
        {
          "type": "paragraph",
          "value": "هو جهاز حقن يشبه القلم، يحوي خرطوشة (عبوة) أنسولين قابلة للاستبدال أو مملوءة مسبقًا، مع إبرة/سنّ يُستبدل. تُحدَّد الجرعة عبر قرص أو تدريج ثم تُحقن تحت الجلد."
        },
        {
          "type": "image",
          "value": "https://i.ibb.co/1fqnhDwn/Screenshot-2025-11-19-214900.png"
        },
        {
          "type": "bullets",
          "value": "المزايا:",
          "items": [
            "سهولة الاستخدام والحمل في الأماكن العامة.",
            "دقة الجرعات وسهولة ضبطها.",
            "إبر قصيرة مُصممة خصيصًا للأقلام (4–8 مم عادةً).",
            "بعض الأقلام قابلة لإعادة الاستخدام بتبديل الخرطوشة؛ أخرى تُستخدم مرة واحدة حتى نفادها."
          ]
        }
      ]
    }
  ]
}
